sns_email_notifier/__init__.py
sns_email_notifier/notification.py
sns_email_notifier-0.1.0.dist-info/METADATA
sns_email_notifier-0.1.0.dist-info/WHEEL
sns_email_notifier-0.1.0.dist-info/top_level.txt
sns_email_notifier-0.1.0.dist-info/RECORD
