Metadata-Version: 2.1
Name: sns-email-notifier
Version: 0.1.0
Summary: A library to send email notifications via AWS SNS.
Author: Aakash
Author-email: aakashbabu75399@gmail.com
Classifier: Programming Language :: Python :: 3
Classifier: License :: OSI Approved :: MIT License
Classifier: Operating System :: OS Independent
Requires-Python: >=3.6
Requires-Dist: boto3
